[
  {
    "variation": "default",
    "version": "sktwi1xtmkfgx8626",
    "items": [
      {}
    ],
    "primary": {
      "text": [
        {
          "type": "heading2",
          "text": "Planning",
          "spans": []
        }
      ],
      "addition_class_text": "dried",
      "image": {
        "dimensions": {
          "width": 900,
          "height": 500
        },
        "alt": null,
        "copyright": null,
        "url": "https://images.unsplash.com/photo-1589321578146-4c1ba445cc88"
      },
      "additional_class_image": "surrounded"
    },
    "slice_type": "about_title_block"
  }
]